gateware/tb/stream_mux.v
/* Stream multiplexer
 * First-word-fallthrough FIFO: data is available on M00_TDATA/TVALID
 * whenever the FIFO is not empty, but the FIFO will not increment unless
 * M00_TREADY is asserted
 */

module stream_mux #(
  // Width of tdata ports
  parameter DW = 32,
  // PACKET_MODE==1: Toggles FIFO on TLAST
  // PACKET_MODE==0: Toggles FIFO on empty
  parameter [0:0] PACKET_MODE=1'b1,
  // The bit to trigger a FIFO toggle if PACKET_MODE==1
  parameter TLAST_BIT=DW-1
) (
  input aclk, // unused
  input aresetn, // unused
  input s00_aclk,
  input s01_aclk,
  input s00_aresetn,
  input s01_aresetn,
  // Input Stream 00
  input s00_tvalid,
  input [DW-1:0] s00_tdata,
  // Input Stream 01
  input s01_tvalid,
  input [DW-1:0] s01_tdata,
  // Output Stream
  input m00_aclk,
  input m00_aresetn,
  output m00_tvalid,
  input m00_tready,
  output [DW-1:0] m00_tdata,
  input s00_arb_req_suppress,
  input s01_arb_req_suppress
);

localparam RAM_WIDTH = DW; // {TLAST, TDATA}

/* FIFO-buffer both S00 and S01 inputs and forward to M00 output
*/

// Two FIFOs
localparam FIFO_DEPTH = 256; // Must be power of 2 for below full/empty scheme to work
localparam FIFO_CW = $clog2(FIFO_DEPTH+1);
// FIFO_00
reg [RAM_WIDTH-1:0] ram00 [0:FIFO_DEPTH-1];
reg [FIFO_CW:0] ipf00=0, opf00=0; // One extra bit for full calculation
wire [FIFO_CW-1:0] ip00=ipf00[FIFO_CW-1:0]; // Input pointer
wire [FIFO_CW-1:0] op00=opf00[FIFO_CW-1:0]; // Output pointer
wire full00=(ip00 == op00) && (ipf00[FIFO_CW] != opf00[FIFO_CW]);
wire empty00=(ipf00 == opf00);
reg [31:0] dropped00=0;
// FIFO_01
reg [RAM_WIDTH-1:0] ram01 [0:FIFO_DEPTH-1];
reg [FIFO_CW:0] ipf01=0, opf01=0; // One extra bit for full calculation
wire [FIFO_CW-1:0] ip01=ipf01[FIFO_CW-1:0]; // Input pointer
wire [FIFO_CW-1:0] op01=opf01[FIFO_CW-1:0]; // Output pointer
wire full01=(ip01 == op01) && (ipf01[FIFO_CW] != opf01[FIFO_CW]);
wire empty01=(ipf01 == opf01);
reg [31:0] dropped01=0;
integer I;
initial begin
  for (I = 0; I < FIFO_DEPTH-1; I = I + 1) begin
    ram00[I] = 0;
    ram01[I] = 0;
  end
end

// Only used when PACKET_MODE==1
wire pktsw00 = ram00[op00][TLAST_BIT];
wire pktsw01 = ram01[op01][TLAST_BIT];

// FIFO_00 Input
always @(posedge s00_aclk) begin
  if (~s00_aresetn) begin
    ipf00 <= 0;
    dropped00 <= 0;
  end else begin
    if (s00_tvalid) begin
      if (!full00) begin
        ram00[ip00] <= s00_tdata;
        ipf00 <= ipf00 + 1; // Intentional rollover
      end else begin // full00
        $display("00 dropped {%d, %x}", s00_tdata);
        dropped00 <= dropped00 + 1;
      end
    end
  end
end

// FIFO_01 Input
always @(posedge s01_aclk) begin
  if (~s01_aresetn) begin
    ipf01 <= 0;
    dropped01 <= 0;
  end else begin
    if (s01_tvalid) begin
      if (!full01) begin
        ram01[ip01] <= s01_tdata;
        ipf01 <= ipf01 + 1; // Intentional rollover
      end else begin // full01
        $display("01 dropped {%d, %x}", s01_tdata);
        dropped01 <= dropped01 + 1;
      end
    end
  end
end

wire [DW-1:0] f00_tdata;
assign f00_tdata = ram00[op00];
wire f00_tvalid = ~empty00;

wire [DW-1:0] f01_tdata;
assign f01_tdata = ram01[op01];
wire f01_tvalid = ~empty01;

reg sel=1'b0;
assign m00_tdata = sel ? f01_tdata : f00_tdata;
assign m00_tvalid = sel ? f01_tvalid : f00_tvalid;

// Output of FIFO_00 and FIFO_01
// Currently only toggles when FIFO is empty. Could change this to
// toggle on TLAST if we want to.
always @(posedge m00_aclk) begin
  if (~m00_aresetn) begin
    opf00 <= 0;
    opf01 <= 0;
    sel <= 1'b0;
  end else begin
    if (~sel) begin
      if (~empty00) begin
        if (m00_tready) begin
          opf00 <= opf00 + 1; // Intentional rollover
        end
        if (PACKET_MODE & pktsw00) begin
          sel <= 1'b1;
          $display("Toggling to 01");
        end
      end else begin  // If empty, toggle sel
        if (!PACKET_MODE) begin
          if ((~s00_arb_req_suppress) && ~empty01) begin
            sel <= 1'b1;
            //$display("Toggling to 01");
          end
        end
      end
    end else begin // if (sel)
      if (~empty01) begin
        if (m00_tready) begin
          opf01 <= opf01 + 1; // Intentional rollover
        end
        if (PACKET_MODE & pktsw01) begin
          sel <= 1'b0;
          $display("Toggling to 00");
        end
      end else begin  // If empty, toggle sel
        if (!PACKET_MODE) begin
          if ((~s01_arb_req_suppress) && ~empty00) begin
            sel <= 1'b0;
            //$display("Toggling to 00");
          end
        end
      end
    end
  end
end

endmodule

gateware/tb/forwardCellLinkMux.v
/* Simulated version of forwardCellLinkMux.v
 * First-word-fallthrough FIFO: data is available on M00_AXIS_TDATA/TVALID
 * whenever the FIFO is not empty, but the FIFO will not increment unless
 * M00_AXIS_TREADY is asserted
 */

module forwardCellLinkMux #(
  // PACKET_MODE==1: Toggles FIFO on TLAST
  // PACKET_MODE==0: Toggles FIFO on empty
  parameter [0:0] PACKET_MODE=1'b1 
) (
  input ACLK, // unused
  input ARESETN, // unused
  input S00_AXIS_ACLK,
  input S01_AXIS_ACLK,
  input S00_AXIS_ARESETN,
  input S01_AXIS_ARESETN,
  // Input Stream 00
  input S00_AXIS_TVALID,
  input [31:0] S00_AXIS_TDATA,
  input S00_AXIS_TLAST,
  // Input Stream 01
  input S01_AXIS_TVALID,
  input [31:0] S01_AXIS_TDATA,
  input S01_AXIS_TLAST,
  // Output Stream
  input M00_AXIS_ACLK,
  input M00_AXIS_ARESETN,
  output M00_AXIS_TVALID,
  input M00_AXIS_TREADY,
  output [31:0] M00_AXIS_TDATA,
  output M00_AXIS_TLAST,
  input S00_ARB_REQ_SUPPRESS,
  input S01_ARB_REQ_SUPPRESS
);

localparam DW = 33; // {TLAST, TDATA}

wire [DW-1:0] m00_tdata;
assign {M00_AXIS_TLAST, M00_AXIS_TDATA} = m00_tdata;

stream_mux #(
  .DW(DW),
  .PACKET_MODE(1'b1),
  .TLAST_BIT(DW-1)
) mux (
  .aclk(ACLK), // input
  .aresetn(ARESETN), // input
  .s00_aclk(S00_AXIS_ACLK), // input
  .s01_aclk(S01_AXIS_ACLK), // input
  .s00_aresetn(S00_AXIS_ARESETN), // input
  .s01_aresetn(S01_AXIS_ARESETN), // input
  .s00_tvalid(S00_AXIS_TVALID), // input
  .s00_tdata({S00_AXIS_TLAST, S00_AXIS_TDATA}), // input [DW-1:0]
  .s01_tvalid(S01_AXIS_TVALID), // input
  .s01_tdata({S01_AXIS_TLAST, S01_AXIS_TDATA}), // input [DW-1:0]
  .m00_aclk(M00_AXIS_ACLK), // input
  .m00_aresetn(M00_AXIS_ARESETN), // input
  .m00_tvalid(M00_AXIS_TVALID), // output
  .m00_tready(M00_AXIS_TREADY), // input
  .m00_tdata(m00_tdata), // output [31:0]
  .s00_arb_req_suppress(S00_ARB_REQ_SUPPRESS), // input
  .s01_arb_req_suppress(S01_ARB_REQ_SUPPRESS) // input
);

endmodule

gateware/tb/fifo_tb.v
`timescale 1ns/1ns

module fifo_tb;

reg clk=1'b0;
always #5 clk <= ~clk;

// VCD dump file for gtkwave
reg [32*8-1:0] dumpfile; // 32-chars max
initial begin
  if (! $value$plusargs("df=%s", dumpfile)) begin
    $display("No dumpfile name supplied; Wave data will not be saved.");
  end else begin
    $dumpfile(dumpfile);
    $dumpvars;
  end
end

localparam TOW = 12;
localparam TOSET = {TOW{1'b1}};
reg [TOW-1:0] timeout=0;
always @(posedge clk) begin
  if (timeout > 0) timeout <= timeout - 1;
end
wire to = ~(|timeout);

reg [31:0] counter=0;
always @(posedge clk) counter <= counter + 1;

reg [31:0] n00_valid=0;
reg [31:0] n01_valid=0;
always @(posedge clk) begin
  if (n00_valid > 0) n00_valid <= n00_valid-1;
  if (n01_valid > 0) n01_valid <= n01_valid-1;
end
wire S00_AXIS_TVALID=(n00_valid > 0);
wire [31:0] S00_AXIS_TDATA=counter;
wire S00_AXIS_TLAST=(n00_valid == 1);
wire S01_AXIS_TVALID=(n01_valid > 0);
wire [31:0] S01_AXIS_TDATA=counter;
wire S01_AXIS_TLAST=(n01_valid == 1);
wire M00_AXIS_TVALID;
wire [31:0] M00_AXIS_TDATA;
wire M00_AXIS_TLAST;
forwardCellLinkMux dut (
  .ACLK(clk), // input
  .ARESETN(1'b1), // input
  .S00_AXIS_ACLK(clk), // input
  .S01_AXIS_ACLK(clk), // input
  .S00_AXIS_ARESETN(1'b1), // input
  .S01_AXIS_ARESETN(1'b1), // input
  .S00_AXIS_TVALID(S00_AXIS_TVALID), // input
  .S00_AXIS_TDATA(S00_AXIS_TDATA), // input [31:0]
  .S00_AXIS_TLAST(S00_AXIS_TLAST), // input
  .S01_AXIS_TVALID(S01_AXIS_TVALID), // input
  .S01_AXIS_TDATA(S01_AXIS_TDATA), // input [31:0]
  .S01_AXIS_TLAST(S01_AXIS_TLAST), // input
  .M00_AXIS_ACLK(clk), // input
  .M00_AXIS_ARESETN(1'b1), // input
  .M00_AXIS_TVALID(M00_AXIS_TVALID), // output
  .M00_AXIS_TREADY(1'b1), // input
  .M00_AXIS_TDATA(M00_AXIS_TDATA), // output [31:0]
  .M00_AXIS_TLAST(M00_AXIS_TLAST), // output
  .S00_ARB_REQ_SUPPRESS(1'b0), // input
  .S01_ARB_REQ_SUPPRESS(1'b0) // input
);

// =========== Stimulus =============
initial begin
          // Start with 16 words on S00
          n00_valid = 16;
          timeout = TOSET;
  #20     wait (dut.mux.empty00 | to);
          // Then 8 words on S01
          n01_valid = 8;
          timeout = TOSET;
  #20     wait (dut.mux.empty01 | to);
          // Then 70 words on both S00 and S01 (can we get it to drop?)
          n00_valid = 70;
          n01_valid = 70;
          timeout = TOSET;
  #20     wait ((dut.mux.empty00 & dut.mux.empty01) | to);
  #100    $display("Done");
          $finish(0);
end

endmodule

gateware/tb/fifo_tb.vcd
$date
	Mon Sep 18 13:46:13 2023
$end
$version
	Icarus Verilog
$end
$timescale
	1ns
$end
$scope module fifo_tb $end
$var wire 32 ! S00_AXIS_TDATA [31:0] $end
$var wire 32 " S01_AXIS_TDATA [31:0] $end
$var wire 1 # to $end
$var wire 1 $ S01_AXIS_TVALID $end
$var wire 1 % S01_AXIS_TLAST $end
$var wire 1 & S00_AXIS_TVALID $end
$var wire 1 ' S00_AXIS_TLAST $end
$var wire 1 ( M00_AXIS_TVALID $end
$var wire 1 ) M00_AXIS_TLAST $end
$var wire 32 * M00_AXIS_TDATA [31:0] $end
$var reg 1 + clk $end
$var reg 32 , counter [31:0] $end
$var reg 256 - dumpfile [255:0] $end
$var reg 32 . n00_valid [31:0] $end
$var reg 32 / n01_valid [31:0] $end
$var reg 12 0 timeout [11:0] $end
$scope module dut $end
$var wire 1 + ACLK $end
$var wire 1 1 ARESETN $end
$var wire 1 + M00_AXIS_ACLK $end
$var wire 1 2 M00_AXIS_ARESETN $end
$var wire 1 3 M00_AXIS_TREADY $end
$var wire 1 4 S00_ARB_REQ_SUPPRESS $end
$var wire 1 + S00_AXIS_ACLK $end
$var wire 1 5 S00_AXIS_ARESETN $end
$var wire 32 6 S00_AXIS_TDATA [31:0] $end
$var wire 1 ' S00_AXIS_TLAST $end
$var wire 1 & S00_AXIS_TVALID $end
$var wire 1 7 S01_ARB_REQ_SUPPRESS $end
$var wire 1 + S01_AXIS_ACLK $end
$var wire 1 8 S01_AXIS_ARESETN $end
$var wire 32 9 S01_AXIS_TDATA [31:0] $end
$var wire 1 % S01_AXIS_TLAST $end
$var wire 1 $ S01_AXIS_TVALID $end
$var wire 33 : m00_tdata [32:0] $end
$var wire 1 ( M00_AXIS_TVALID $end
$var wire 1 ) M00_AXIS_TLAST $end
$var wire 32 ; M00_AXIS_TDATA [31:0] $end
$scope module mux $end
$var wire 1 + aclk $end
$var wire 1 1 aresetn $end
$var wire 33 < f00_tdata [32:0] $end
$var wire 1 = f00_tvalid $end
$var wire 33 > f01_tdata [32:0] $end
$var wire 1 ? f01_tvalid $end
$var wire 1 @ full00 $end
$var wire 1 A full01 $end
$var wire 1 + m00_aclk $end
$var wire 1 2 m00_aresetn $end
$var wire 1 3 m00_tready $end
$var wire 1 + s00_aclk $end
$var wire 1 4 s00_arb_req_suppress $end
$var wire 1 5 s00_aresetn $end
$var wire 33 B s00_tdata [32:0] $end
$var wire 1 & s00_tvalid $end
$var wire 1 + s01_aclk $end
$var wire 1 7 s01_arb_req_suppress $end
$var wire 1 8 s01_aresetn $end
$var wire 33 C s01_tdata [32:0] $end
$var wire 1 $ s01_tvalid $end
$var wire 1 D pktsw01 $end
$var wire 1 E pktsw00 $end
$var wire 9 F op01 [8:0] $end
$var wire 9 G op00 [8:0] $end
$var wire 1 ( m00_tvalid $end
$var wire 33 H m00_tdata [32:0] $end
$var wire 9 I ip01 [8:0] $end
$var wire 9 J ip00 [8:0] $end
$var wire 1 K empty01 $end
$var wire 1 L empty00 $end
$var reg 32 M dropped00 [31:0] $end
$var reg 32 N dropped01 [31:0] $end
$var reg 10 O ipf00 [9:0] $end
$var reg 10 P ipf01 [9:0] $end
$var reg 10 Q opf00 [9:0] $end
$var reg 10 R opf01 [9:0] $end
$var reg 1 S sel $end
$var integer 32 T I [31:0] $end
$upscope $end
$upscope $end
$upscope $end
$enddefinitions $end
#0
$dumpvars
b11111111 T
0S
b0 R
b0 Q
b0 P
b0 O
b0 N
b0 M
1L
1K
b0 J
b0 I
b0 H
b0 G
b0 F
0E
0D
b0 C
b0 B
0A
0@
0?
b0 >
0=
b0 <
b0 ;
b0 :
b0 9
18
07
b0 6
15
04
13
12
11
b111111111111 0
b0 /
b10000 .
b110011001101001011001100110111101011111011101000110001000101110011101100110001101100100 -
b0 ,
0+
b0 *
0)
0(
0'
1&
0%
0$
0#
b0 "
b0 !
$end
#5
1(
b1 J
1=
0L
b1 O
b111111111110 0
b1 C
b1 "
b1 9
b1 B
b1 !
b1 6
b1 ,
b1111 .
1+
#10
0+
#15
b1 *
b1 ;
b1 :
b1 H
b1 <
b1 G
b10 J
b1110 .
b10 C
b10 "
b10 9
b10 B
b10 !
b10 6
b10 ,
b111111111101 0
b1 Q
b10 O
1+
#20
0+
#25
b10 *
b10 ;
b10 :
b10 H
b11 J
b10 <
b10 G
b11 O
0L
b10 Q
b111111111100 0
b11 C
b11 "
b11 9
b11 B
b11 !
b11 6
b11 ,
b1101 .
1+
#30
0+
#35
b11 *
b11 ;
b11 :
b11 H
b11 <
b11 G
b100 J
b1100 .
b100 C
b100 "
b100 9
b100 B
b100 !
b100 6
b100 ,
b111111111011 0
b11 Q
b100 O
1+
#40
0+
#45
b100 *
b100 ;
b100 :
b100 H
b101 J
b100 <
b100 G
b101 O
0L
b100 Q
b111111111010 0
b101 C
b101 "
b101 9
b101 B
b101 !
b101 6
b101 ,
b1011 .
1+
#50
0+
#55
b101 *
b101 ;
b101 :
b101 H
b101 <
b101 G
b110 J
b1010 .
b110 C
b110 "
b110 9
b110 B
b110 !
b110 6
b110 ,
b111111111001 0
b101 Q
b110 O
1+
#60
0+
#65
b110 *
b110 ;
b110 :
b110 H
b111 J
b110 <
b110 G
b111 O
0L
b110 Q
b111111111000 0
b111 C
b111 "
b111 9
b111 B
b111 !
b111 6
b111 ,
b1001 .
1+
#70
0+
#75
b111 *
b111 ;
b111 :
b111 H
b111 <
b111 G
b1000 J
b1000 .
b1000 C
b1000 "
b1000 9
b1000 B
b1000 !
b1000 6
b1000 ,
b111111110111 0
b111 Q
b1000 O
1+
#80
0+
#85
b1000 *
b1000 ;
b1000 :
b1000 H
b1001 J
b1000 <
b1000 G
b1001 O
0L
b1000 Q
b111111110110 0
b1001 C
b1001 "
b1001 9
b1001 B
b1001 !
b1001 6
b1001 ,
b111 .
1+
#90
0+
#95
b1001 *
b1001 ;
b1001 :
b1001 H
b1001 <
b1001 G
b1010 J
b110 .
b1010 C
b1010 "
b1010 9
b1010 B
b1010 !
b1010 6
b1010 ,
b111111110101 0
b1001 Q
b1010 O
1+
#100
0+
#105
b1010 *
b1010 ;
b1010 :
b1010 H
b1011 J
b1010 <
b1010 G
b1011 O
0L
b1010 Q
b111111110100 0
b1011 C
b1011 "
b1011 9
b1011 B
b1011 !
b1011 6
b1011 ,
b101 .
1+
#110
0+
#115
b1011 *
b1011 ;
b1011 :
b1011 H
b1011 <
b1011 G
b1100 J
b100 .
b1100 C
b1100 "
b1100 9
b1100 B
b1100 !
b1100 6
b1100 ,
b111111110011 0
b1011 Q
b1100 O
1+
#120
0+
#125
b1100 *
b1100 ;
b1100 :
b1100 H
b1101 J
b1100 <
b1100 G
b1101 O
0L
b1100 Q
b111111110010 0
b1101 C
b1101 "
b1101 9
b1101 B
b1101 !
b1101 6
b1101 ,
b11 .
1+
#130
0+
#135
b1101 *
b1101 ;
b1101 :
b1101 H
b1101 <
b1101 G
b1110 J
b10 .
b1110 C
b1110 "
b1110 9
b1110 B
b1110 !
b1110 6
b1110 ,
b111111110001 0
b1101 Q
b1110 O
1+
#140
0+
#145
b1110 *
b1110 ;
b1110 :
b1110 H
b1111 J
b1110 <
b1110 G
b1111 O
0L
b1110 Q
b111111110000 0
b1111 C
b1111 "
b1111 9
b1111 !
b1111 6
b1111 ,
b100000000000000000000000000001111 B
1'
b1 .
1+
#150
0+
#155
1)
b1111 *
b1111 ;
1E
b100000000000000000000000000001111 :
b100000000000000000000000000001111 H
b100000000000000000000000000001111 <
b1111 G
b10000 J
0&
0'
b0 .
b10000 C
b10000 "
b10000 9
b10000 B
b10000 !
b10000 6
b10000 ,
b111111101111 0
b1111 Q
b10000 O
1+
#160
0+
#165
0)
b0 *
b0 ;
0E
b0 :
b0 H
0(
b0 <
b10000 G
0=
1$
b1000 /
1S
1L
b10000 Q
b111111111111 0
b10001 C
b10001 "
b10001 9
b10001 B
b10001 !
b10001 6
b10001 ,
1+
#170
0+
#175
1(
b10001 *
b10001 ;
b1 I
1?
b10001 :
b10001 H
b111 /
b10010 C
b10010 "
b10010 9
b10010 B
b10010 !
b10010 6
b10010 ,
b111111111110 0
0K
b1 P
b10001 >
1+
#180
0+
#185
b10010 *
b10010 ;
b10010 :
b10010 H
b10 I
b10010 >
b1 F
b10 P
0K
b1 R
b111111111101 0
b10011 C
b10011 "
b10011 9
b10011 B
b10011 !
b10011 6
b10011 ,
b110 /
1+
#190
0+
#195
b10011 *
b10011 ;
b10011 :
b10011 H
b10011 >
b10 F
b11 I
b101 /
b10100 C
b10100 "
b10100 9
b10100 B
b10100 !
b10100 6
b10100 ,
b111111111100 0
b10 R
b11 P
1+
#200
0+
#205
b10100 *
b10100 ;
b10100 :
b10100 H
b100 I
b10100 >
b11 F
b100 P
0K
b11 R
b111111111011 0
b10101 C
b10101 "
b10101 9
b10101 B
b10101 !
b10101 6
b10101 ,
b100 /
1+
#210
0+
#215
b10101 *
b10101 ;
b10101 :
b10101 H
b10101 >
b100 F
b101 I
b11 /
b10110 C
b10110 "
b10110 9
b10110 B
b10110 !
b10110 6
b10110 ,
b111111111010 0
b100 R
b101 P
1+
#220
0+
#225
b10110 *
b10110 ;
b10110 :
b10110 H
b110 I
b10110 >
b101 F
b110 P
0K
b101 R
b111111111001 0
b10111 C
b10111 "
b10111 9
b10111 B
b10111 !
b10111 6
b10111 ,
b10 /
1+
#230
0+
#235
b10111 *
b10111 ;
b10111 :
b10111 H
b10111 >
b110 F
b111 I
1%
b1 /
b100000000000000000000000000011000 C
b11000 "
b11000 9
b11000 B
b11000 !
b11000 6
b11000 ,
b111111111000 0
b110 R
b111 P
1+
#240
0+
#245
1)
b11000 *
b11000 ;
1D
b100000000000000000000000000011000 :
b100000000000000000000000000011000 H
b1000 I
b100000000000000000000000000011000 >
b111 F
b1000 P
0K
b111 R
b111111110111 0
b11001 "
b11001 9
b11001 B
b11001 !
b11001 6
b11001 ,
0$
b11001 C
0%
b0 /
1+
#250
0+
#255
0)
b0 *
b0 ;
0D
b0 :
b0 H
0(
b0 >
b1000 F
0?
1$
b1000110 /
1&
b1000110 .
b11010 C
b11010 "
b11010 9
b11010 B
b11010 !
b11010 6
b11010 ,
b111111111111 0
0S
1K
b1000 R
1+
#260
0+
#265
1(
b11010 *
b11010 ;
b10001 J
1=
b11010 :
b11010 H
b1001 I
1?
0L
b10001 O
b11010 <
0K
b1001 P
b11010 >
b111111111110 0
b11011 C
b11011 "
b11011 9
b11011 B
b11011 !
b11011 6
b11011 ,
b1000101 /
b1000101 .
1+
#270
0+
#275
b11011 *
b11011 ;
b11011 :
b11011 H
b11011 <
b10001 G
b1010 I
b10010 J
b1000100 /
b1000100 .
b11100 C
b11100 "
b11100 9
b11100 B
b11100 !
b11100 6
b11100 ,
b111111111101 0
b10001 Q
b1010 P
b10010 O
1+
#280
0+
#285
b11100 *
b11100 ;
b11100 :
b11100 H
b10011 J
b1011 I
b11100 <
b10010 G
b10011 O
b1011 P
0L
b10010 Q
b111111111100 0
b11101 C
b11101 "
b11101 9
b11101 B
b11101 !
b11101 6
b11101 ,
b1000011 /
b1000011 .
1+
#290
0+
#295
b11101 *
b11101 ;
b11101 :
b11101 H
b11101 <
b10011 G
b1100 I
b10100 J
b1000010 /
b1000010 .
b11110 C
b11110 "
b11110 9
b11110 B
b11110 !
b11110 6
b11110 ,
b111111111011 0
b10011 Q
b1100 P
b10100 O
1+
#300
0+
#305
b11110 *
b11110 ;
b11110 :
b11110 H
b10101 J
b1101 I
b11110 <
b10100 G
b10101 O
b1101 P
0L
b10100 Q
b111111111010 0
b11111 C
b11111 "
b11111 9
b11111 B
b11111 !
b11111 6
b11111 ,
b1000001 /
b1000001 .
1+
#310
0+
#315
b11111 *
b11111 ;
b11111 :
b11111 H
b11111 <
b10101 G
b1110 I
b10110 J
b1000000 /
b1000000 .
b100000 C
b100000 "
b100000 9
b100000 B
b100000 !
b100000 6
b100000 ,
b111111111001 0
b10101 Q
b1110 P
b10110 O
1+
#320
0+
#325
b100000 *
b100000 ;
b100000 :
b100000 H
b10111 J
b1111 I
b100000 <
b10110 G
b10111 O
b1111 P
0L
b10110 Q
b111111111000 0
b100001 C
b100001 "
b100001 9
b100001 B
b100001 !
b100001 6
b100001 ,
b111111 /
b111111 .
1+
#330
0+
#335
b100001 *
b100001 ;
b100001 :
b100001 H
b100001 <
b10111 G
b10000 I
b11000 J
b111110 /
b111110 .
b100010 C
b100010 "
b100010 9
b100010 B
b100010 !
b100010 6
b100010 ,
b111111110111 0
b10111 Q
b10000 P
b11000 O
1+
#340
0+
#345
b100010 *
b100010 ;
b100010 :
b100010 H
b11001 J
b10001 I
b100010 <
b11000 G
b11001 O
b10001 P
0L
b11000 Q
b111111110110 0
b100011 C
b100011 "
b100011 9
b100011 B
b100011 !
b100011 6
b100011 ,
b111101 /
b111101 .
1+
#350
0+
#355
b100011 *
b100011 ;
b100011 :
b100011 H
b100011 <
b11001 G
b10010 I
b11010 J
b111100 /
b111100 .
b100100 C
b100100 "
b100100 9
b100100 B
b100100 !
b100100 6
b100100 ,
b111111110101 0
b11001 Q
b10010 P
b11010 O
1+
#360
0+
#365
b100100 *
b100100 ;
b100100 :
b100100 H
b11011 J
b10011 I
b100100 <
b11010 G
b11011 O
b10011 P
0L
b11010 Q
b111111110100 0
b100101 C
b100101 "
b100101 9
b100101 B
b100101 !
b100101 6
b100101 ,
b111011 /
b111011 .
1+
#370
0+
#375
b100101 *
b100101 ;
b100101 :
b100101 H
b100101 <
b11011 G
b10100 I
b11100 J
b111010 /
b111010 .
b100110 C
b100110 "
b100110 9
b100110 B
b100110 !
b100110 6
b100110 ,
b111111110011 0
b11011 Q
b10100 P
b11100 O
1+
#380
0+
#385
b100110 *
b100110 ;
b100110 :
b100110 H
b11101 J
b10101 I
b100110 <
b11100 G
b11101 O
b10101 P
0L
b11100 Q
b111111110010 0
b100111 C
b100111 "
b100111 9
b100111 B
b100111 !
b100111 6
b100111 ,
b111001 /
b111001 .
1+
#390
0+
#395
b100111 *
b100111 ;
b100111 :
b100111 H
b100111 <
b11101 G
b10110 I
b11110 J
b111000 /
b111000 .
b101000 C
b101000 "
b101000 9
b101000 B
b101000 !
b101000 6
b101000 ,
b111111110001 0
b11101 Q
b10110 P
b11110 O
1+
#400
0+
#405
b101000 *
b101000 ;
b101000 :
b101000 H
b11111 J
b10111 I
b101000 <
b11110 G
b11111 O
b10111 P
0L
b11110 Q
b111111110000 0
b101001 C
b101001 "
b101001 9
b101001 B
b101001 !
b101001 6
b101001 ,
b110111 /
b110111 .
1+
#410
0+
#415
b101001 *
b101001 ;
b101001 :
b101001 H
b101001 <
b11111 G
b11000 I
b100000 J
b110110 /
b110110 .
b101010 C
b101010 "
b101010 9
b101010 B
b101010 !
b101010 6
b101010 ,
b111111101111 0
b11111 Q
b11000 P
b100000 O
1+
#420
0+
#425
b101010 *
b101010 ;
b101010 :
b101010 H
b100001 J
b11001 I
b101010 <
b100000 G
b100001 O
b11001 P
0L
b100000 Q
b111111101110 0
b101011 C
b101011 "
b101011 9
b101011 B
b101011 !
b101011 6
b101011 ,
b110101 /
b110101 .
1+
#430
0+
#435
b101011 *
b101011 ;
b101011 :
b101011 H
b101011 <
b100001 G
b11010 I
b100010 J
b110100 /
b110100 .
b101100 C
b101100 "
b101100 9
b101100 B
b101100 !
b101100 6
b101100 ,
b111111101101 0
b100001 Q
b11010 P
b100010 O
1+
#440
0+
#445
b101100 *
b101100 ;
b101100 :
b101100 H
b100011 J
b11011 I
b101100 <
b100010 G
b100011 O
b11011 P
0L
b100010 Q
b111111101100 0
b101101 C
b101101 "
b101101 9
b101101 B
b101101 !
b101101 6
b101101 ,
b110011 /
b110011 .
1+
#450
0+
#455
b101101 *
b101101 ;
b101101 :
b101101 H
b101101 <
b100011 G
b11100 I
b100100 J
b110010 /
b110010 .
b101110 C
b101110 "
b101110 9
b101110 B
b101110 !
b101110 6
b101110 ,
b111111101011 0
b100011 Q
b11100 P
b100100 O
1+
#460
0+
#465
b101110 *
b101110 ;
b101110 :
b101110 H
b100101 J
b11101 I
b101110 <
b100100 G
b100101 O
b11101 P
0L
b100100 Q
b111111101010 0
b101111 C
b101111 "
b101111 9
b101111 B
b101111 !
b101111 6
b101111 ,
b110001 /
b110001 .
1+
#470
0+
#475
b101111 *
b101111 ;
b101111 :
b101111 H
b101111 <
b100101 G
b11110 I
b100110 J
b110000 /
b110000 .
b110000 C
b110000 "
b110000 9
b110000 B
b110000 !
b110000 6
b110000 ,
b111111101001 0
b100101 Q
b11110 P
b100110 O
1+
#480
0+
#485
b110000 *
b110000 ;
b110000 :
b110000 H
b100111 J
b11111 I
b110000 <
b100110 G
b100111 O
b11111 P
0L
b100110 Q
b111111101000 0
b110001 C
b110001 "
b110001 9
b110001 B
b110001 !
b110001 6
b110001 ,
b101111 /
b101111 .
1+
#490
0+
#495
b110001 *
b110001 ;
b110001 :
b110001 H
b110001 <
b100111 G
b100000 I
b101000 J
b101110 /
b101110 .
b110010 C
b110010 "
b110010 9
b110010 B
b110010 !
b110010 6
b110010 ,
b111111100111 0
b100111 Q
b100000 P
b101000 O
1+
#500
0+
#505
b110010 *
b110010 ;
b110010 :
b110010 H
b101001 J
b100001 I
b110010 <
b101000 G
b101001 O
b100001 P
0L
b101000 Q
b111111100110 0
b110011 C
b110011 "
b110011 9
b110011 B
b110011 !
b110011 6
b110011 ,
b101101 /
b101101 .
1+
#510
0+
#515
b110011 *
b110011 ;
b110011 :
b110011 H
b110011 <
b101001 G
b100010 I
b101010 J
b101100 /
b101100 .
b110100 C
b110100 "
b110100 9
b110100 B
b110100 !
b110100 6
b110100 ,
b111111100101 0
b101001 Q
b100010 P
b101010 O
1+
#520
0+
#525
b110100 *
b110100 ;
b110100 :
b110100 H
b101011 J
b100011 I
b110100 <
b101010 G
b101011 O
b100011 P
0L
b101010 Q
b111111100100 0
b110101 C
b110101 "
b110101 9
b110101 B
b110101 !
b110101 6
b110101 ,
b101011 /
b101011 .
1+
#530
0+
#535
b110101 *
b110101 ;
b110101 :
b110101 H
b110101 <
b101011 G
b100100 I
b101100 J
b101010 /
b101010 .
b110110 C
b110110 "
b110110 9
b110110 B
b110110 !
b110110 6
b110110 ,
b111111100011 0
b101011 Q
b100100 P
b101100 O
1+
#540
0+
#545
b110110 *
b110110 ;
b110110 :
b110110 H
b101101 J
b100101 I
b110110 <
b101100 G
b101101 O
b100101 P
0L
b101100 Q
b111111100010 0
b110111 C
b110111 "
b110111 9
b110111 B
b110111 !
b110111 6
b110111 ,
b101001 /
b101001 .
1+
#550
0+
#555
b110111 *
b110111 ;
b110111 :
b110111 H
b110111 <
b101101 G
b100110 I
b101110 J
b101000 /
b101000 .
b111000 C
b111000 "
b111000 9
b111000 B
b111000 !
b111000 6
b111000 ,
b111111100001 0
b101101 Q
b100110 P
b101110 O
1+
#560
0+
#565
b111000 *
b111000 ;
b111000 :
b111000 H
b101111 J
b100111 I
b111000 <
b101110 G
b101111 O
b100111 P
0L
b101110 Q
b111111100000 0
b111001 C
b111001 "
b111001 9
b111001 B
b111001 !
b111001 6
b111001 ,
b100111 /
b100111 .
1+
#570
0+
#575
b111001 *
b111001 ;
b111001 :
b111001 H
b111001 <
b101111 G
b101000 I
b110000 J
b100110 /
b100110 .
b111010 C
b111010 "
b111010 9
b111010 B
b111010 !
b111010 6
b111010 ,
b111111011111 0
b101111 Q
b101000 P
b110000 O
1+
#580
0+
